credentials/__init__.py
credentials/__main__.py
credentials/base.py
credentials/credential.py
pycredentials-0.1.0.dist-info/METADATA
pycredentials-0.1.0.dist-info/WHEEL
pycredentials-0.1.0.dist-info/entry_points.txt
pycredentials-0.1.0.dist-info/RECORD
